any2toon/__init__.py
any2toon/config.py
any2toon/converters.py
any2toon/core.py
any2toon/exceptions.py
any2toon/sniffer.py
any2toon/toon_serializer.py
any2toon-0.1.3.dist-info/licenses/LICENSE
any2toon-0.1.3.dist-info/METADATA
any2toon-0.1.3.dist-info/WHEEL
any2toon-0.1.3.dist-info/top_level.txt
any2toon-0.1.3.dist-info/RECORD
