Metadata-Version: 2.4
Name: any2toon
Version: 0.1.3
Summary: A robust library to convert JSON, YAML, XML, CSV, Avro, Parquet, BSON, and NDJSON to TOON format.
Project-URL: Homepage, https://github.com/AleLoredo/any2toon
Classifier: Programming Language :: Python :: 3
Classifier: License :: OSI Approved :: MIT License
Classifier: Operating System :: OS Independent
Requires-Python: >=3.7
License-File: LICENSE
Requires-Dist: PyYAML>=6.0.0
Requires-Dist: xmltodict>=0.13.0
Provides-Extra: avro
Requires-Dist: fastavro>=1.0.0; extra == "avro"
Provides-Extra: parquet
Requires-Dist: pyarrow>=10.0.0; extra == "parquet"
Provides-Extra: bson
Requires-Dist: pymongo>=4.0.0; extra == "bson"
Provides-Extra: lite
Requires-Dist: fastavro>=1.0.0; extra == "lite"
Requires-Dist: pyarrow>=10.0.0; extra == "lite"
Requires-Dist: pymongo>=4.0.0; extra == "lite"
Provides-Extra: polars
Requires-Dist: polars>=0.19.0; extra == "polars"
Provides-Extra: pandas
Requires-Dist: pandas>=2.0.0; extra == "pandas"
Provides-Extra: all
Requires-Dist: fastavro>=1.0.0; extra == "all"
Requires-Dist: pyarrow>=10.0.0; extra == "all"
Requires-Dist: pymongo>=4.0.0; extra == "all"
Requires-Dist: polars>=0.19.0; extra == "all"
Dynamic: license-file
